[{"id":"1282616","name":"Waling","latitude":"27.983330","longitude":"83.766670","country":"NP"},{"id":"1282635","name":"Tulsipur","latitude":"28.130989","longitude":"82.297256","country":"NP"},{"id":"1282666","name":"Tikapur","latitude":"28.500000","longitude":"81.133331","country":"NP"},{"id":"1282714","name":"Tansen","latitude":"27.867310","longitude":"83.546700","country":"NP"},{"id":"1282770","name":"Siraha","latitude":"26.654110","longitude":"86.208702","country":"NP"},{"id":"1282884","name":"Rajbiraj","latitude":"26.533331","longitude":"86.750000","country":"NP"},{"id":"1282898","name":"Pokhara","latitude":"28.233334","longitude":"83.983330","country":"NP"},{"id":"1282931","name":"Patan","latitude":"27.666668","longitude":"85.333336","country":"NP"},{"id":"1282950","name":"Panaoti","latitude":"27.581381","longitude":"85.512398","country":"NP"},{"id":"1283011","name":"Namche Bazar","latitude":"27.816668","longitude":"86.716667","country":"NP"},{"id":"1283018","name":"Nagarkot","latitude":"27.700001","longitude":"85.516670","country":"NP"},{"id":"1283082","name":"Malangwa","latitude":"26.856791","longitude":"85.558113","country":"NP"},{"id":"1283095","name":"Mahendranagar","latitude":"28.916670","longitude":"80.333328","country":"NP"},{"id":"1283161","name":"Lahan","latitude":"26.729580","longitude":"86.495148","country":"NP"},{"id":"1283190","name":"Kirtipur","latitude":"27.666668","longitude":"85.283333","country":"NP"},{"id":"1283217","name":"Khandbari","latitude":"27.374689","longitude":"87.203903","country":"NP"},{"id":"1283240","name":"Kathmandu","latitude":"27.716667","longitude":"85.316666","country":"NP"},{"id":"1283285","name":"Jumla","latitude":"29.274719","longitude":"82.183830","country":"NP"},{"id":"1283318","name":"Janakpur","latitude":"26.718281","longitude":"85.906464","country":"NP"},{"id":"1283323","name":"Jaleswar","latitude":"26.647110","longitude":"85.800812","country":"NP"},{"id":"1283329","name":"Ithari","latitude":"26.666670","longitude":"87.283333","country":"NP"},{"id":"1283333","name":"Ilam","latitude":"26.909430","longitude":"87.928238","country":"NP"},{"id":"1283339","name":"Hitura","latitude":"27.428391","longitude":"85.032188","country":"NP"},{"id":"1283368","name":"Gulariya","latitude":"28.233330","longitude":"81.333328","country":"NP"},{"id":"1283401","name":"Gaur","latitude":"26.766670","longitude":"85.266670","country":"NP"},{"id":"1283460","name":"Dharan Bazar","latitude":"26.812481","longitude":"87.283546","country":"NP"},{"id":"1283465","name":"Dhankuta","latitude":"26.983330","longitude":"87.333328","country":"NP"},{"id":"1283467","name":"Dhangarhi","latitude":"28.707920","longitude":"80.596107","country":"NP"},{"id":"1283484","name":"Darchula","latitude":"29.841209","longitude":"80.528740","country":"NP"},{"id":"1283496","name":"Dailekh","latitude":"28.844339","longitude":"81.710114","country":"NP"},{"id":"1283499","name":"Dadeldhura","latitude":"29.298420","longitude":"80.580589","country":"NP"},{"id":"1283562","name":"Butwal","latitude":"27.700550","longitude":"83.448357","country":"NP"},{"id":"1283581","name":"Birganj","latitude":"27.010429","longitude":"84.877350","country":"NP"},{"id":"1283582","name":"Biratnagar","latitude":"26.483101","longitude":"87.283371","country":"NP"},{"id":"1283599","name":"Bhojpur","latitude":"27.935650","longitude":"81.775551","country":"NP"},{"id":"1283600","name":"Bhojpur","latitude":"27.171499","longitude":"87.046066","country":"NP"},{"id":"1283613","name":"Bharatpur","latitude":"27.683332","longitude":"84.433334","country":"NP"},{"id":"1283621","name":"Bhairahawa","latitude":"27.500000","longitude":"83.449997","country":"NP"},{"id":"1283628","name":"Bhadrapur","latitude":"26.544041","longitude":"88.094360","country":"NP"},{"id":"1283679","name":"Banepa","latitude":"27.629789","longitude":"85.521378","country":"NP"},{"id":"1283711","name":"Baglung","latitude":"28.271891","longitude":"83.589760","country":"NP"},{"id":"6254843","name":"Birendranagar","latitude":"28.601940","longitude":"81.633888","country":"NP"},{"id":"6941099","name":"Nepalgunj","latitude":"28.049999","longitude":"81.616669","country":"NP"},{"id":"6941691","name":"Chitre","latitude":"28.426729","longitude":"83.690758","country":"NP"},{"id":"8199102","name":"kankrabari Dovan","latitude":"27.628811","longitude":"85.459343","country":"NP"}]