[{"id":"363533","name":"Zalingei","latitude":"12.909600","longitude":"23.474060","country":"SD"},{"id":"364027","name":"Wagar","latitude":"16.152500","longitude":"36.203201","country":"SD"},{"id":"364071","name":"Wad Rawah","latitude":"15.160280","longitude":"33.139721","country":"SD"},{"id":"364103","name":"Wad Medani","latitude":"14.401180","longitude":"33.519890","country":"SD"},{"id":"364216","name":"Wad az Zaki","latitude":"14.461900","longitude":"32.206501","country":"SD"},{"id":"364706","name":"Umm Ruwaba","latitude":"12.906100","longitude":"31.215799","country":"SD"},{"id":"364933","name":"Umm Kaddadah","latitude":"13.601690","longitude":"26.687590","country":"SD"},{"id":"364949","name":"Um Jar Al Gharbiyya","latitude":"13.801300","longitude":"32.407799","country":"SD"},{"id":"365137","name":"Omdurman","latitude":"15.644530","longitude":"32.477730","country":"SD"},{"id":"366323","name":"Tokar","latitude":"18.425400","longitude":"37.729000","country":"SD"},{"id":"366426","name":"Tandalti","latitude":"13.016670","longitude":"31.866671","country":"SD"},{"id":"366487","name":"Talodi","latitude":"10.632460","longitude":"30.379700","country":"SD"},{"id":"366847","name":"Sinja","latitude":"13.150000","longitude":"33.933331","country":"SD"},{"id":"367308","name":"Shendi","latitude":"16.691500","longitude":"33.434101","country":"SD"},{"id":"367544","name":"Sawakin","latitude":"19.105900","longitude":"37.332100","country":"SD"},{"id":"367644","name":"Sinnar","latitude":"13.569070","longitude":"33.567181","country":"SD"},{"id":"368277","name":"Rabak","latitude":"13.180870","longitude":"32.739990","country":"SD"},{"id":"370481","name":"Marawi","latitude":"18.483330","longitude":"31.816669","country":"SD"},{"id":"370510","name":"Marabba","latitude":"12.350000","longitude":"32.183331","country":"SD"},{"id":"370838","name":"Maiurno","latitude":"13.416670","longitude":"33.666672","country":"SD"},{"id":"371745","name":"Kutum","latitude":"14.200000","longitude":"24.666670","country":"SD"},{"id":"371760","name":"Kosti","latitude":"13.162900","longitude":"32.663471","country":"SD"},{"id":"371827","name":"Kurmuk","latitude":"10.550000","longitude":"34.283329","country":"SD"},{"id":"371870","name":"Kuraymah","latitude":"18.549999","longitude":"31.850000","country":"SD"},{"id":"372386","name":"Kinana","latitude":"14.036100","longitude":"33.171200","country":"SD"},{"id":"372753","name":"Kassala","latitude":"15.450990","longitude":"36.399979","country":"SD"},{"id":"372801","name":"Karmah an Nuzul","latitude":"19.633329","longitude":"30.416670","country":"SD"},{"id":"373141","name":"Kadugli","latitude":"11.016670","longitude":"29.716669","country":"SD"},{"id":"375046","name":"Gebeit","latitude":"21.066669","longitude":"36.316669","country":"SD"},{"id":"375192","name":"Jalqani","latitude":"12.448600","longitude":"34.218601","country":"SD"},{"id":"376332","name":"Doka","latitude":"13.516670","longitude":"35.766670","country":"SD"},{"id":"376450","name":"Dilling","latitude":"12.050000","longitude":"29.650000","country":"SD"},{"id":"377039","name":"Port Sudan","latitude":"19.617451","longitude":"37.216438","country":"SD"},{"id":"377690","name":"Berber","latitude":"18.021580","longitude":"33.982990","country":"SD"},{"id":"377724","name":"Barah","latitude":"13.700000","longitude":"30.366671","country":"SD"},{"id":"378231","name":"Atbara","latitude":"17.702169","longitude":"33.986382","country":"SD"},{"id":"378271","name":"As Suki","latitude":"13.316670","longitude":"33.883331","country":"SD"},{"id":"378459","name":"Ar Ruseris","latitude":"11.865900","longitude":"34.386902","country":"SD"},{"id":"378493","name":"Ar Rahad","latitude":"12.716670","longitude":"30.650000","country":"SD"},{"id":"378502","name":"Aroma","latitude":"15.816670","longitude":"36.133331","country":"SD"},{"id":"378543","name":"Argo","latitude":"19.516670","longitude":"30.416670","country":"SD"},{"id":"378699","name":"An Nuhud","latitude":"12.700000","longitude":"28.433331","country":"SD"},{"id":"379003","name":"El Obeid","latitude":"13.184210","longitude":"30.216690","country":"SD"},{"id":"379014","name":"Al Qitena","latitude":"14.864800","longitude":"32.366798","country":"SD"},{"id":"379080","name":"Al Masallamiyya","latitude":"14.574800","longitude":"33.337299","country":"SD"},{"id":"379102","name":"Al Mijlad","latitude":"11.033330","longitude":"27.733330","country":"SD"},{"id":"379127","name":"El Matama","latitude":"16.709499","longitude":"33.356499","country":"SD"},{"id":"379149","name":"Al Manaqil","latitude":"14.245900","longitude":"32.989101","country":"SD"},{"id":"379198","name":"Al Lagowa","latitude":"11.400000","longitude":"29.133329","country":"SD"},{"id":"379252","name":"Khartoum","latitude":"15.551770","longitude":"32.532410","country":"SD"},{"id":"379261","name":"Al Kiremit al Arakiyyin","latitude":"14.347600","longitude":"32.943699","country":"SD"},{"id":"379272","name":"Al Kawa","latitude":"13.746300","longitude":"32.499599","country":"SD"},{"id":"379303","name":"El Geneina","latitude":"13.450000","longitude":"22.450001","country":"SD"},{"id":"379406","name":"Al Hilaliyya","latitude":"14.939800","longitude":"33.234001","country":"SD"},{"id":"379416","name":"Al Hawatah","latitude":"13.416670","longitude":"34.633331","country":"SD"},{"id":"379427","name":"Al Hasaheisa","latitude":"14.752640","longitude":"33.298359","country":"SD"},{"id":"379535","name":"Al Fulah","latitude":"11.732920","longitude":"28.357861","country":"SD"},{"id":"379555","name":"El Fasher","latitude":"13.627930","longitude":"25.349360","country":"SD"},{"id":"379630","name":"El Bauga","latitude":"18.261959","longitude":"33.908119","country":"SD"},{"id":"380129","name":"Ad Diwem","latitude":"14.001200","longitude":"32.311600","country":"SD"},{"id":"380151","name":"Ad Dindar","latitude":"13.200000","longitude":"34.166672","country":"SD"},{"id":"380173","name":"Ed Damer","latitude":"17.592779","longitude":"33.959171","country":"SD"},{"id":"380174","name":"Ad-Damazin","latitude":"11.789100","longitude":"34.359200","country":"SD"},{"id":"380186","name":"Ad Dabbah","latitude":"18.049999","longitude":"30.950001","country":"SD"},{"id":"380348","name":"Abu Zabad","latitude":"12.350000","longitude":"29.250000","country":"SD"},{"id":"380757","name":"Abu Jibeha","latitude":"11.456200","longitude":"31.228500","country":"SD"}]